YJL.py
YJL-2023.11.7.dist-info/LICENSE
YJL-2023.11.7.dist-info/METADATA
YJL-2023.11.7.dist-info/WHEEL
YJL-2023.11.7.dist-info/top_level.txt
YJL-2023.11.7.dist-info/RECORD
